psopy/__init__.py
psopy/constraints.py
psopy/minimize.py
psopy/utilities.py
psopy-0.2.4.dist-info/LICENSE.txt
psopy-0.2.4.dist-info/METADATA
psopy-0.2.4.dist-info/WHEEL
psopy-0.2.4.dist-info/top_level.txt
psopy-0.2.4.dist-info/RECORD
