Metadata-Version: 2.1
Name: psopy
Version: 0.2.4
Summary: A SciPy compatible super fast Python implementation for Particle Swarm Optimization. 
Home-page: https://github.com/jerrytheo/psopy
Author: Abhijit Theophilus, Dr. Snehanshu Saha, Suryoday Basak
Author-email: abhijit.theo@gmail.com, snehanshusaha@gmail.com, suryodaybasak@gmail.com
License: UNKNOWN
Keywords: optimization-algorithms,particle-swarm-optimization,constrained-optimization
Platform: UNKNOWN
Classifier: Development Status :: 4 - Beta
Classifier: Intended Audience :: Science/Research
Classifier: Topic :: Scientific/Engineering :: Mathematics
Classifier: License :: OSI Approved :: BSD License
Classifier: Operating System :: Microsoft :: Windows
Classifier: Operating System :: POSIX
Classifier: Operating System :: Unix
Classifier: Programming Language :: Python :: 3
Classifier: Programming Language :: Python :: 3.4
Classifier: Programming Language :: Python :: 3.5
Classifier: Programming Language :: Python :: 3.6
Classifier: Programming Language :: Python :: 3.7
Requires-Dist: scipy
Requires-Dist: numpy
